type_changer/__init__.py
type_changer/caster.py
type_changer/validator.py
type_changer-0.0.2.dist-info/LICENSE
type_changer-0.0.2.dist-info/METADATA
type_changer-0.0.2.dist-info/WHEEL
type_changer-0.0.2.dist-info/RECORD
