Metadata-Version: 2.1
Name: type-changer
Version: 0.0.2
Summary: Changes the data-type in a json or dictionary using Pydantic Basemodel.
License: AGPL-3.0-or-later
Author: Code63Reaper
Author-email: akilangms542@gmail.com
Maintainer: Code63Reaper
Maintainer-email: akilangms542@gmail.com
Requires-Python: >=3.10,<4.0
Classifier: Development Status :: 2 - Pre-Alpha
Classifier: Intended Audience :: Developers
Classifier: License :: OSI Approved :: GNU Affero General Public License v3 or later (AGPLv3+)
Classifier: Programming Language :: Python :: 3
Classifier: Programming Language :: Python :: 3.10
Classifier: Programming Language :: Python :: 3.11
Classifier: Programming Language :: Python :: 3.12
Classifier: Programming Language :: Python :: 3 :: Only
Classifier: Topic :: Utilities
Requires-Dist: pydantic (>=2.8.2,<3.0.0)
